MANIFEST.in
README.rst
VERSION
setup.py
caicloud/__init__.py
caicloud.tensorflow.egg-info/PKG-INFO
caicloud.tensorflow.egg-info/SOURCES.txt
caicloud.tensorflow.egg-info/dependency_links.txt
caicloud.tensorflow.egg-info/requires.txt
caicloud.tensorflow.egg-info/top_level.txt
caicloud/clever/__init__.py
caicloud/clever/examples/README.md
caicloud/clever/examples/__init__.py
caicloud/clever/examples/boston_house/__init__.py
caicloud/clever/examples/boston_house/boston_house.py
caicloud/clever/examples/boston_house/boston_house_bak.py
caicloud/clever/examples/boston_house/grpc_client.py
caicloud/clever/examples/boston_house/test.py
caicloud/clever/examples/boston_house/train_model.sh
caicloud/clever/examples/half_plus_two/README.md
caicloud/clever/examples/half_plus_two/__init__.py
caicloud/clever/examples/half_plus_two/grpc_client.py
caicloud/clever/examples/half_plus_two/import_model_half_plus_two.py
caicloud/clever/examples/half_plus_two/restful_client.py
caicloud/clever/examples/half_plus_two/saved_model_half_plus_two.py
caicloud/clever/examples/half_plus_two/test_model.sh
caicloud/clever/examples/half_plus_two/train_model.sh
caicloud/clever/examples/mnist/README.md
caicloud/clever/examples/mnist/__init__.py
caicloud/clever/examples/mnist/grpc_client.py
caicloud/clever/examples/mnist/mnist_export.py
caicloud/clever/examples/mnist/mnist_import.py
caicloud/clever/examples/mnist/restful_client.py
caicloud/clever/examples/mnist/test_model.sh
caicloud/clever/examples/mnist/train_model.sh
caicloud/clever/examples/ptb/README.md
caicloud/clever/examples/ptb/__init__.py
caicloud/clever/examples/ptb/grpc_client.py
caicloud/clever/examples/ptb/ptb_caicloud_taas.py
caicloud/clever/examples/ptb/ptb_word_lm.py
caicloud/clever/examples/ptb/reader.py
caicloud/clever/examples/ptb/reader_test.py
caicloud/clever/examples/ptb/test-grpc.sh
caicloud/clever/examples/ptb/train-model.sh
caicloud/clever/examples/ptb/simple-examples/1-train/test.sh
caicloud/clever/examples/ptb/simple-examples/1-train/train.sh
caicloud/clever/examples/ptb/simple-examples/2-nbest-rescore/lattices/nbest.sh
caicloud/clever/examples/ptb/simple-examples/3-combination/test.sh
