Metadata-Version: 1.1
Name: caicloud.tensorflow
Version: 2.1.0
Summary: Caicloud TensorFlow as a Service (TaaS) dev environment
Home-page: https://caicloud.io/
Author: Caicloud Inc.
Author-email: taas@caicloud.io
License: Apache 2.0
Keywords: caicloud tensorflow serving machine learing
Platform: UNKNOWN
Classifier: Development Status :: 4 - Beta
Classifier: Intended Audience :: Developers
Classifier: Intended Audience :: Education
Classifier: Intended Audience :: Science/Research
Classifier: License :: OSI Approved :: Apache Software License
Classifier: Programming Language :: Python :: 2.7
Classifier: Topic :: Scientific/Engineering :: Mathematics
Classifier: Topic :: Software Development :: Libraries :: Python Modules
Classifier: Topic :: Software Development :: Libraries
